[
	{
		"name": "Chaos Angel",
		"index": 22850702,
		"monsterAttribute": "Dark",
		"monsterType": "Fiend",
		"type": [
			"Synchro",
			"Effect"
		],
		"summonRequirement": "1 Tuner + 1+ non-Tuner LIGHT or DARK monsters",
		"lore": "For this card's Synchro Summon, you can treat 1 LIGHT or DARK monster you control as a Tuner. If this card is Special Summoned: You can target 1 card on the field; banish it. This card gains these effects based on the original Attributes of materials used for its Synchro Summon. • LIGHT: Synchro Monsters you control are unaffected by monster effects activated by your opponent. • DARK: Monsters you control cannot be destroyed by battle.",
		"level": 10,
		"attack": 3500,
		"defense": 2800
	}
]